Metadata-Version: 2.1
Name: odoo-addon-account_statement_import_ofx
Version: 18.0.1.0.0.4
Requires-Python: >=3.10
Requires-Dist: odoo-addon-account_statement_import_file==18.0.*
Requires-Dist: odoo==18.0.*
Requires-Dist: ofxparse
Summary: Import OFX Bank Statement
Home-page: https://github.com/OCA/bank-statement-import
License: AGPL-3
Author: Odoo SA,Akretion,La Louve,GRAP,Nicolas JEUDY,Le Filament,Odoo Community Association (OCA)
Author-email: support@odoo-community.org
Classifier: Programming Language :: Python
Classifier: Framework :: Odoo
Classifier: Framework :: Odoo :: 18.0
Classifier: License :: OSI Approved :: GNU Affero General Public License v3
Classifier: Development Status :: 6 - Mature
